{"html": [{"t": "<div><div class=\"p\">OTORGA AMPLIACI&#xD3;N DE CONCESI&#xD3;N DE SERVICIOS SANITARIOS</div></div>", "i": 10108669}, {"t": "<div><br><br><div class=\"p\"> </div><div class=\"p\">&nbsp; &nbsp;  Por decreto supremo N&#xBA; 1, del Ministerio de Obras P&#xFA;blicas, de fecha 8 de enero de 2020, tramitado el 27 de enero de 2020, se otorg&#xF3; a Essbio S.A., RUT N&#xBA; 76.833.300-9, domiciliada en Arturo Prat 199, torre B, piso 15, oficina 1501, Concepci&#xF3;n, Regi&#xF3;n del Biob&#xED;o, la ampliaci&#xF3;n de las concesiones de producci&#xF3;n y distribuci&#xF3;n de agua potable y de recolecci&#xF3;n y disposici&#xF3;n de aguas servidas, destinadas a la atenci&#xF3;n del &#xE1;rea denominada &quot;Varios sectores de Coya&quot;, de la localidad de Coya, comuna de Machal&#xED;, Regi&#xF3;n del Libertador General Bernardo O&apos;Higgins. La zona de concesi&#xF3;n o territorio operacional de los servicios de distribuci&#xF3;n de agua potable y de recolecci&#xF3;n de aguas servidas, corresponder&#xE1; a un &#xE1;rea de aproximadamente 2,4 hect&#xE1;reas, que se encuentra identificada y delimitada en el plano denominado &quot;Solicitud Ampliaci&#xF3;n Territorio Operacional Concesi&#xF3;n de servicios p&#xFA;blicos sanitarios para la producci&#xF3;n y distribuci&#xF3;n de agua potable y la recolecci&#xF3;n y disposici&#xF3;n de aguas servidas para un &#xE1;rea geogr&#xE1;fica identificada como: &quot;Varios Sectores Coya&quot; Sistemas de Agua Potable y Aguas Servidas Provincia: Cachapoal Comuna: Machal&#xED;&quot;, del Plan de Desarrollo, que forma parte integrante del presente decreto. En el primer establecimiento (a&#xF1;o 2024), se considera la instalaci&#xF3;n de 10 arranques de agua potable e igual n&#xFA;mero de uniones domiciliarias de alcantarillado, cantidad que se mantendr&#xE1;, en ambos casos, hasta el final del per&#xED;odo (a&#xF1;o 2034). El servicio p&#xFA;blico de producci&#xF3;n de agua potable para el sistema que se ampl&#xED;a por este decreto, ser&#xE1; abastecido por la fuente que se indica en el numeral 3.1. letra a), de la respectiva Ficha de Antecedentes T&#xE9;cnicos (FAT), sobre la cual la concesionaria tiene los derechos que se individualizan en el informe de t&#xED;tulos respectivo, que son suficientes para satisfacer la demanda de servicio, en los t&#xE9;rminos exigidos por el art&#xED;culo 26&#xBA; del DS MOP N&#xBA; 1.199/04, y se encuentran afectos a la concesi&#xF3;n, documentos que forman parte integrante del presente decreto. Las dem&#xE1;s condiciones de prestaci&#xF3;n de los servicios otorgados en la ampliaci&#xF3;n, son las establecidas en la Ficha de Antecedentes T&#xE9;cnicos (FAT) N&#xBA; SC 06 - 24 A, que forma parte integrante del presente decreto. Programa de Desarrollo, cronograma de inversiones, nivel tarifario, garant&#xED;as y otros en decreto extractado, que se redujo a escritura p&#xFA;blica con fecha 4 de febrero de 2020 ante el Notario de Rancagua, don Ernesto Montoya Peredo.</div><div class=\"p\"> </div></div>", "i": 10108670}, {"t": "<div><div class=\"p\">&nbsp; &nbsp;  Santiago, febrero de 2020.- Jorge Rivas Chaparro, Superintendente de Servicios Sanitarios (S).</div><br></div>", "i": 10108671}], "proyectos": [], "otrosSistemas": [], "jurisprudencia": [], "doctrina": [], "metadatos": {"tiene_notas": false, "tipos_numeros": [{"tipo": "2", "numero": "1", "abreviacion": "DTO", "descripcion": "Decreto", "compuesto": "Decreto-1"}], "organismos": ["MINISTERIO DE OBRAS PÚBLICAS", "SUPERINTENDENCIA DE SERVICIOS SANITARIOS"], "titulo_norma": "OTORGA AMPLIACIÓN DE CONCESIÓN DE SERVICIOS SANITARIOS", "fuente": "Diario Oficial", "resumenes": [], "materias": [], "terminos_libres": [], "categorias_norma": [], "nombres_uso_comun": [], "paises_tratados": [], "organismos_tratados": [], "observaciones": ["CVE 1734821; EXTRACTO"], "derogacion_tacita": [], "derogado": false, "fecha_promulgacion": "2020-01-27", "doble_articulado": false, "id_norma": "1143456", "numero_fuente": "42605", "tipo_version": "3", "tipo_version_s": "Única", "fecha_publicacion": "2020-03-16", "vigencias": [{"desde": "2020-03-16", "hasta": "", "tipo_version": "3", "tipo_version_s": "Única"}], "vigencia": {"inicio_vigencia": "2020-03-16", "fin_vigencia": ""}, "vigencias_version_norma": [{"inicio_vigencia": "2020-03-16", "fin_vigencia": "", "tipo_version": "3"}], "eventos_pendientes": [], "vinculaciones": [], "ingresado_por": "1795", "fecha_ingreso": "2020-03-16", "fecha_version": "2020-03-16", "fecha_actualizacion_texto": "2020-03-16", "tipo_tratado": ""}, "alertas": [], "alerta_global": "", "estructura": [{"n": "Encabezado", "i": 10108669}, {"n": "Artículo", "i": 10108670, "t": 6}, {"n": "Promulgación", "i": 10108671}]}