{"html": [{"t": "<div><div class=\"p\">MODIFICA ANEXOS 51-7, 51-29 Y 51-36, DEL COMPENDIO DE NORMAS ADUANERAS</div></div>", "i": 10261690}, {"t": "<div><div class=\"p\">&nbsp; &nbsp;  Mediante resoluci&#xF3;n exenta N&#xB0; 1.898, de 09.08.2021, del Director Nacional de Aduanas, se modificaron los Anexos 51-7, 51-29 y 51-36 en el siguiente sentido:</div><div class=\"p\">&nbsp; &nbsp; &nbsp; </div><div class=\"p\">&nbsp; &nbsp;  Rempl&#xE1;zase, el nombre de la empresa Lan Chile por Latam Airlines Group S.A.</div><div class=\"p\">&nbsp; &nbsp;  Incorp&#xF3;rase, la empresa Alimentos del Mar Limitada como Proveedores de Naves.</div><div class=\"p\">&nbsp; &nbsp;  Agr&#xE9;gase, las empresas Saco Shipping SpA; Klog. Co S.A.; Cumbres Logistics Ltda.; Ducis Logistics Chile SpA, como transitarios y forwarder.</div><div class=\"p\">&nbsp; &nbsp;  Modif&#xED;case, los datos relativos a la resoluci&#xF3;n de la empresa Contekner SpA.</div><div class=\"p\">&nbsp; &nbsp; &nbsp; </div><div class=\"p\">&nbsp; &nbsp;  El texto &#xED;ntegro de esta resoluci&#xF3;n se encuentra publicado en el sitio web del Servicio Nacional de Aduanas (www.aduana.cl).</div><div class=\"p\">&nbsp; &nbsp; &nbsp; </div><br></div>", "i": 10261691}, {"t": "<div><div class=\"p\">&nbsp; &nbsp;  Valpara&#xED;so, 12 de agosto de 2021.- Jos&#xE9; Ignacio Palma Sotomayor, Director Nacional de Aduanas.</div><div class=\"p\"> </div><br></div>", "i": 10261692}], "proyectos": [], "otrosSistemas": [], "jurisprudencia": [], "doctrina": [], "metadatos": {"tiene_notas": false, "tipos_numeros": [{"tipo": "3", "numero": "1898 EXENTA", "abreviacion": "RES", "descripcion": "Resolución", "compuesto": "Resolución-1898 EXENTA"}], "organismos": ["MINISTERIO DE HACIENDA", "SERVICIO NACIONAL DE ADUANAS", "DIRECCIÓN NACIONAL"], "titulo_norma": "MODIFICA ANEXOS 51-7, 51-29 Y 51-36, DEL COMPENDIO DE NORMAS ADUANERAS", "fuente": "Diario Oficial", "resumenes": [], "materias": [], "terminos_libres": [], "categorias_norma": [], "nombres_uso_comun": [], "paises_tratados": [], "organismos_tratados": [], "observaciones": ["CVE 1994616", "EXTRACTO"], "derogacion_tacita": [], "derogado": false, "fecha_promulgacion": "2021-08-09", "doble_articulado": false, "id_norma": "1163939", "numero_fuente": "43031", "tipo_version": "3", "tipo_version_s": "Única", "fecha_publicacion": "2021-08-18", "vigencias": [{"desde": "2021-08-18", "hasta": "", "tipo_version": "3", "tipo_version_s": "Única"}], "vigencia": {"inicio_vigencia": "2021-08-18", "fin_vigencia": ""}, "vigencias_version_norma": [{"inicio_vigencia": "2021-08-18", "fin_vigencia": "", "tipo_version": "3"}], "eventos_pendientes": [], "vinculaciones": [{"text": "MODIFICACION", "url_part": "modificacion"}], "ingresado_por": "1795", "fecha_ingreso": "2021-08-18", "fecha_version": "2021-08-18", "fecha_actualizacion_texto": "2021-08-18", "tipo_tratado": ""}, "alertas": [], "alerta_global": "", "estructura": [{"n": "Encabezado", "i": 10261690}, {"n": "Artículo", "i": 10261691, "t": 6}, {"n": "Promulgación", "i": 10261692}]}