{"html": [{"t": "<div><div class=\"p\">DERECHOS DE APROVECHAMIENTO DE AGUAS EN LA COMUNA DE CABRERO </div></div>", "i": 6132762}, {"t": "<div><div class=\"p\">&nbsp; &nbsp;  Servicio Agr&#xED;cola y Ganadero mediante resoluci&#xF3;n</div><div class=\"p\">exenta No. 2.107 de 12 de Diciembre de 1988, conforme</div><div class=\"p\">Art. 5&#xB0; Transitorio C&#xF3;digo de Aguas, determin&#xF3; Derechos Aprovechamiento Aguas proporcionales que corresponden a Sector Excluido y Sector Expropiado predios &quot;Potrero El Cantarito y Parte de los Potreros El Alamo y Pangalito de la Hijuela Cuarta o Centinela de Colicheu&quot; y &quot;Resto del Predio Centinela o Hijuela Cuarta de Colicheu&quot; de la comuna de Cabrero, VIII Regi&#xF3;n; y Derechos Aprovechamiento Aguas que corresponden a parcelas No. s 1 a la 52, sitios N&#xB0;s 1 y 4 al 29 y Reserva Cora 1 del Proyecto de Parcelaci&#xF3;n &quot;El Progreso&quot; formado por predios se&#xF1;alados entre otros. Los Derechos de Agua se extraen del canal Za&#xF1;artu derivado del r&#xED;o Laja y de derrames generados fuera y dentro del predio.Publicaci&#xF3;n hecha conforme Art. 13 Ley No. 18.377.-</div><br></div>", "i": 6132763}, {"t": "<div><div class=\"p\">&nbsp; &nbsp;  Director Ejecutivo.</div><br></div>", "i": 6132764}], "proyectos": [], "otrosSistemas": [], "jurisprudencia": [], "doctrina": [], "metadatos": {"tiene_notas": false, "tipos_numeros": [{"tipo": "3", "numero": "2107 EXENTA", "abreviacion": "RES", "descripcion": "Resolucion", "compuesto": "RES-2107 EXENTA"}], "organismos": ["MINISTERIO DE AGRICULTURA", "SERVICIO AGRICOLA Y GANADERO"], "titulo_norma": "DERECHOS DE APROVECHAMIENTO DE AGUAS EN LA COMUNA DE CABRERO", "fuente": "Diario Oficial", "resumenes": [], "materias": [], "terminos_libres": [], "categorias_norma": [], "nombres_uso_comun": [], "paises_tratados": [], "organismos_tratados": [], "observaciones": [], "derogacion_tacita": [], "derogado": false, "fecha_promulgacion": "1988-12-12", "doble_articulado": false, "id_norma": "125103", "numero_fuente": "33246", "tipo_version": "3", "tipo_version_s": "Única", "fecha_publicacion": "1988-12-15", "vigencias": [{"desde": "1988-12-15", "hasta": "", "tipo_version": "3", "tipo_version_s": "Única"}], "vigencia": {"inicio_vigencia": "1988-12-15", "fin_vigencia": ""}, "vigencias_version_norma": [{"inicio_vigencia": "1988-12-15", "fin_vigencia": "", "tipo_version": "3"}], "eventos_pendientes": [], "vinculaciones": [], "ingresado_por": "FMR", "fecha_ingreso": "1998-10-01", "fecha_version": "1988-12-15", "fecha_actualizacion_texto": "1988-12-15", "tipo_tratado": ""}, "alertas": [], "alerta_global": "", "estructura": [{"n": "Encabezado", "i": 6132762}, {"n": "Artículo", "i": 6132763, "t": 6}, {"n": "Promulgación", "i": 6132764}]}