{"html": [{"t": "<div><div class=\"p\">AUTO ACORDADO SOBRE REAJUSTE DE CUANTIA DE LOS ASUNTOS NO DETERMINADOS DE SUELDOS VITALES DE LOS CODIGOS QUE INDICA </div><br><div class=\"p\">&nbsp; &nbsp;  &quot;En Santiago a veintinueve de Enero de mil novecientos ochenta y cinco, se reuni&#xF3; la Corte Suprema en Pleno presidida por don Rafael Retamal L&#xF3;pez y con la asistencia de los Ministros se&#xF1;ores Eyzaguirre, B&#xF3;rquez, Ram&#xED;rez, Correa, Erbeta, Ulloa, Meersohn, Letelier, Cereceda, Jord&#xE1;n y Zurita, y en cumplimiento de lo dispuesto en el art&#xED;culo sexto del decrero ley N&#xB0; 1.417 de 09 de Abril de 1976, modificado por el decreto ley N&#xB0; 2.416, de 13 de Diciembre de 1978, el Tribunal reajusta la cuant&#xED;a de los asuntos no determinados en sueldos vitales en &#xE9;l referidos, por medio del siguiente auto acordado:</div><br></div>", "i": 7266538}, {"t": "<div><div class=\"p\">&nbsp; &nbsp;  &quot;Primero.- &quot;Introd&#xFA;cense en el art&#xED;culo que se se&#xF1;ala del C&#xF3;digo Org&#xE1;nico de Tribunales, las siguientes modificaciones:</div><br><div class=\"p\">&nbsp; &nbsp;  Art&#xED;culo 198.- &quot;En el inciso final, reemplazado por el decreto ley N&#xB0; 1.417, se sustituyen los guarismos &quot;$ 519&quot; y &quot;$ 387&quot;, por &quot;$ 638&quot; y &quot;$ 476&quot;, respectivamente. </div><br></div>", "i": 7266539, "v": ["MODIFICACION"]}, {"t": "<div><div class=\"p\">&nbsp; &nbsp;  &quot;Segundo.- &quot;Introd&#xFA;cense las siguientes modificaciones al C&#xF3;digo de Procedimiento Civil:</div><br><div class=\"p\">&nbsp; &nbsp;  &quot;Art&#xED;culo 88.- &quot;En el inciso final se reemplaza &quot;$ 2.585&quot; por &quot;$ 3.180&quot;.</div><div class=\"p\">&nbsp; &nbsp;  &quot;Art&#xED;culo 118.- &quot;En el inciso segundo se reemplazan las cantidades: &quot;$ 891&quot;, &quot;$ 683&quot;, &quot;$ 519&quot;, &quot;$ 399&quot;, &quot;$ 208&quot;, &quot;$ 77&quot;, por &quot;$ 1.096&quot;, &quot;$ 840&quot;, &quot;$ 638&quot;, &quot;$ 491&quot;, &quot;$ 256&quot;, &quot;$ 95&quot;, respectivamente.</div><div class=\"p\">&nbsp; &nbsp;  &quot;Art&#xED;culo 165.- &quot;En el inciso segundo del N&#xB0; 4, se sustituyen &quot;$ 282&quot;, &quot;$ 119&quot; por &quot;$ 347&quot; y &quot;$ 146&quot;, respectivamente.</div><div class=\"p\">&nbsp; &nbsp;  &quot;Art&#xED;culo 445.- &quot;En los n&#xFA;meros 9 y 12, se reemplaza &quot;$ 86.667&quot; por &quot;$ 106.600.</div><div class=\"p\">&nbsp; &nbsp;  &quot;Art&#xED;culo 698.- En el inciso primero se reemplaza &quot;$ 2.585&quot; y &quot;$ 52.004&quot; por &quot;$ 3.180&quot; y &quot;$ 63.695, respectivamente.</div><div class=\"p\">&nbsp; &nbsp;  &quot;Art&#xED;culo 703.- &quot;Se reemplaza &quot;$ 2.585&quot; por &quot;$ 3.180&quot;.</div><div class=\"p\">&nbsp; &nbsp;  &quot;Art&#xED;culo 749.- &quot;Se reemplaza &quot;$ 52.004&quot; por &quot;S 63.695&quot;.</div><div class=\"p\">&nbsp; &nbsp;  &quot;Art&#xED;culo 767.- &quot;En los incisos tercero, quinto y sexto, se reemplaza $ 17.309&quot; por &quot;$ 21.290&quot;.</div><div class=\"p\">&nbsp; &nbsp;  &quot;Art&#xED;culo 801.- &quot;En el inciso primero se reemplaza &quot;$ 3.476&quot; por &quot;$ 4.275&quot;.</div><div class=\"p\">&nbsp; &nbsp;  &quot;En el inciso cuarto se sustituye &quot;$ 208&quot; por &quot;$ 256&quot;. </div><br></div>", "i": 7266540, "v": ["MODIFICACION"]}, {"t": "<div><div class=\"p\">&nbsp; &nbsp;  &quot;Tercero: &quot;Introd&#xFA;cense las siguientes modificaciones al C&#xF3;digo de procedimiento Penal:</div><br><div class=\"p\">&nbsp; &nbsp;  &quot;Art&#xED;culo 245.- &quot;En el inciso quinto se reemplaza &quot;$ 17.309&quot; por &quot;$ 21.290&quot;.</div><div class=\"p\">&nbsp; &nbsp;  &quot;Art&#xED;culo 537.- &quot;Se reemplazan &quot;$ 386&quot;, &quot;$ 208&quot;, &quot;$ 81&quot;, por &quot;$ 475&quot;, &quot;$ 256&quot; y &quot;$ 100&quot;, respectivamente. </div></div>", "i": 7266541}, {"t": "<div><div class=\"p\">&nbsp; &nbsp;  &quot;Publ&#xED;quese en el Diario Oficial.</div><div class=\"p\">&nbsp; &nbsp;  &quot;Para constancia se extiende la presente acta.- (Fdo.) R. Retamal L., J. Eyzaguirre E., I B&#xF3;rquez M., O Ram&#xED;rez M., E. Correa L., O. Erbetta L., E. Ulloa M., A. Meersohn Sch., C. Letelier B., H. Cereceda B., S. Jord&#xE1;n L., E. Zurita C.- R. Pica U.&quot; </div></div>", "i": 7266542}], "proyectos": [], "otrosSistemas": [], "jurisprudencia": [], "doctrina": [], "metadatos": {"tiene_notas": false, "tipos_numeros": [{"tipo": "4", "numero": "S/N", "abreviacion": "AA", "descripcion": "Auto Acordado", "compuesto": "AA-S/N"}], "organismos": ["CORTE SUPREMA"], "titulo_norma": "AUTO ACORDADO SOBRE REAJUSTE DE CUANTIA DE LOS ASUNTOS NO\nDETERMINADOS DE SUELDOS VITALES DE LOS CODIGOS QUE INDICA", "fuente": "Diario Oficial", "resumenes": [], "materias": [], "terminos_libres": [], "categorias_norma": [], "nombres_uso_comun": [], "paises_tratados": [], "organismos_tratados": [], "observaciones": [], "derogacion_tacita": [], "derogado": false, "fecha_promulgacion": "1985-01-29", "doble_articulado": false, "id_norma": "163495", "numero_fuente": "32088", "tipo_version": "3", "tipo_version_s": "Única", "fecha_publicacion": "1985-02-04", "vigencias": [{"desde": "1985-02-04", "hasta": "", "tipo_version": "3", "tipo_version_s": "Única"}], "vigencia": {"inicio_vigencia": "1985-02-04", "fin_vigencia": ""}, "vigencias_version_norma": [{"inicio_vigencia": "1985-02-04", "fin_vigencia": "", "tipo_version": "3"}], "eventos_pendientes": [], "vinculaciones": [{"text": "MODIFICACION", "url_part": "modificacion"}], "ingresado_por": "PMZ", "fecha_ingreso": "2000-03-31", "fecha_version": "1985-02-04", "fecha_actualizacion_texto": "1985-02-04", "tipo_tratado": ""}, "alertas": [], "alerta_global": "", "estructura": [{"n": "Encabezado", "i": 7266538}, {"n": "Artículo PRIMERO", "i": 7266539, "t": 6}, {"n": "Artículo SEGUNDO", "i": 7266540, "t": 6}, {"n": "Artículo TERCERO", "i": 7266541, "t": 6}, {"n": "Promulgación", "i": 7266542}]}