{"html": [{"t": "<div><div class=\"p\">&#xA0;</div></div>", "i": 6404454}, {"t": "<div><div class=\"p\">&nbsp; &nbsp;  Por decreto MOP exento N&#xBA; 1.518, de 29 de octubre</div><div class=\"p\">de 2002, y en base a la facultad otorgada por el</div><div class=\"p\">art&#xED;culo 105 del DFL MOP N&#xBA; 850 de 1997, que fij&#xF3; el texto actualizado de la ley N&#xBA; 15.840, se expropiaron los lotes de terreno N&#xBA;s. 38, 46, 51A, 51B y 51C para la obra: Camino Ruta T-55, Sector Futrono-Llif&#xE9;n, Tramo Km.</div><div class=\"p\">55,30000 a Km. 75,76384, que figuran a nombre de Club Pesca y Caza Ainilebu, Pitrip&#xE1;n Curinao Marcedes, Manque Vidal Geralda, roles de aval&#xFA;o 61-173, 61-43 y 61-57, Comuna de Futrono, X Regi&#xF3;n, superficies 196,50 m2; 65 m2.; 126 m2.; 133 y 274,50 m2. La comisi&#xF3;n de peritos fij&#xF3; con fecha 12 de febrero de 2001, el monto de la indemnizaci&#xF3;n provisional en la cantidad de $815.450.-, para el lote 38; $307.500.-, para el lote 46;</div><div class=\"p\">$277.000.-, para el lote 51A; $287.000.-, para el lote 51B y $589.000.-, para el lote 51C. Las indemnizaciones se pagar&#xE1;n al contado. La publicaci&#xF3;n se efect&#xFA;a en cumplimiento a lo dispuesto en el art&#xED;culo 7&#xBA; del decreto ley N&#xBA; 2.186, de 1978.-</div><br></div>", "i": 6404455}, {"t": "<div><div class=\"p\">&nbsp; &nbsp;  Fiscal del Ministerio de Obras P&#xFA;blicas. </div></div>", "i": 6404456}], "proyectos": [], "otrosSistemas": [], "jurisprudencia": [], "doctrina": [], "metadatos": {"tiene_notas": false, "tipos_numeros": [{"tipo": "2", "numero": "1518 EXENTO", "abreviacion": "DTO", "descripcion": "Decreto", "compuesto": "DTO-1518 EXENTO"}], "organismos": ["MINISTERIO DE OBRAS PÚBLICAS", "FISCALÍA"], "titulo_norma": "", "fuente": "Diario Oficial", "resumenes": [], "materias": [], "terminos_libres": [], "categorias_norma": [], "nombres_uso_comun": [], "paises_tratados": [], "organismos_tratados": [], "observaciones": ["EXTRACTO"], "derogacion_tacita": [], "derogado": false, "fecha_promulgacion": "2002-10-29", "doble_articulado": false, "id_norma": "205110", "numero_fuente": "37423", "tipo_version": "3", "tipo_version_s": "Única", "fecha_publicacion": "2002-12-02", "vigencias": [{"desde": "2002-12-02", "hasta": "", "tipo_version": "3", "tipo_version_s": "Única"}], "vigencia": {"inicio_vigencia": "2002-12-02", "fin_vigencia": ""}, "vigencias_version_norma": [{"inicio_vigencia": "2002-12-02", "fin_vigencia": "", "tipo_version": "3"}], "eventos_pendientes": [], "vinculaciones": [], "ingresado_por": "MAS", "fecha_ingreso": "2002-12-02", "fecha_version": "2002-12-02", "fecha_actualizacion_texto": "2002-12-02", "tipo_tratado": ""}, "alertas": [], "alerta_global": "", "estructura": [{"n": "Encabezado", "i": 6404454}, {"n": "Artículo", "i": 6404455, "t": 6}, {"n": "Promulgación", "i": 6404456}]}