{"html": [{"t": "<div><div class=\"p\">&#xA0;</div></div>", "i": 5942488}, {"t": "<div><div class=\"p\">&nbsp; &nbsp; Por Decreto Exento N&#xB0; 186 de fecha 21 de Abril de 1993 del Ministerio de Educaci&#xF3;n, se aprob&#xF3; al Centro de Formaci&#xF3;n T&#xE9;cnica AIEP, el Plan y Programas de Estudio de la Carrera y T&#xED;tulo T&#xE9;cnico de Nivel Superior que se indica, para ser impartida en la Sede N&#xB0; 7 de Calama y Sede N&#xB0; 6 de San Fernando, a contar del a&#xF1;o 1993:</div><div class=\"p\"> Carrera&nbsp; &nbsp; : Asistente del Educador de P&#xE1;rvulos.</div><div class=\"p\"> T&#xED;tulo&nbsp; &nbsp;  : Asistente del Educador de P&#xE1;rvulos.</div><br></div>", "i": 5942489}, {"t": "<div><div class=\"p\">&nbsp; &nbsp; Julio Valladares Mu&#xF1;oz, Subsecretario de Educaci&#xF3;n. + </div></div>", "i": 5942490}], "proyectos": [], "otrosSistemas": [], "jurisprudencia": [], "doctrina": [], "metadatos": {"tiene_notas": false, "tipos_numeros": [{"tipo": "2", "numero": "186 EXENTO", "abreviacion": "DTO", "descripcion": "Decreto", "compuesto": "DTO-186 EXENTO"}], "organismos": ["MINISTERIO DE EDUCACIÓN"], "titulo_norma": "", "fuente": "Diario Oficial", "resumenes": [], "materias": [], "terminos_libres": ["CENTRO FORMACION TECNICA AIEP", "ASISTENTE EDUCADOR", "PARVULOS", "CALAMA", "SEGUNDA REGION"], "categorias_norma": [], "nombres_uso_comun": [], "paises_tratados": [], "organismos_tratados": [], "observaciones": [], "derogacion_tacita": [], "derogado": false, "fecha_promulgacion": "1993-04-21", "doble_articulado": false, "id_norma": "20599", "numero_fuente": "34635", "tipo_version": "3", "tipo_version_s": "Única", "fecha_publicacion": "1993-08-07", "vigencias": [{"desde": "1993-08-07", "hasta": "", "tipo_version": "3", "tipo_version_s": "Única"}], "vigencia": {"inicio_vigencia": "1993-08-07", "fin_vigencia": ""}, "vigencias_version_norma": [{"inicio_vigencia": "1993-08-07", "fin_vigencia": "", "tipo_version": "3"}], "eventos_pendientes": [], "vinculaciones": [], "fecha_version": "1993-08-07", "fecha_actualizacion_texto": "1993-08-07", "tipo_tratado": ""}, "alertas": [], "alerta_global": "", "estructura": [{"n": "Encabezado", "i": 5942488}, {"n": "Artículo", "i": 5942489, "t": 6}, {"n": "Promulgación", "i": 5942490}]}