{"html": [{"t": "<div><br><div class=\"p\">EXTRACTO DE DECRETO N&#xBA; 408 EXENTO, DE 2003 </div></div>", "i": 6431436}, {"t": "<div><div class=\"p\">&nbsp; &nbsp;  Por decreto exento N&#xBA; 408, de fecha 6 de junio de 2003, del Ministerio de Educaci&#xF3;n, se aprueban los planes y programas de estudios al Centro de Formaci&#xF3;n T&#xE9;cnica Barros Arana de las carreras y t&#xED;tulos t&#xE9;cnicos de nivel superior que se indican, para ser impartidas a contar del a&#xF1;o 2003, en la Sede Central de Concepci&#xF3;n:</div><br><div class=\"p\">Carrera&nbsp;  : T&#xE9;cnico Jur&#xED;dico</div><div class=\"p\">T&#xED;tulo&nbsp; &nbsp; : T&#xE9;cnico Jur&#xED;dico</div><br><div class=\"p\">Carrera&nbsp;  : T&#xE9;cnico en Enfermer&#xED;a</div><div class=\"p\">T&#xED;tulo&nbsp; &nbsp; : T&#xE9;cnico de Nivel Superior en Enfermer&#xED;a</div><br><div class=\"p\">&nbsp; &nbsp;  Por este mismo decreto, se aprueban a contar del a&#xF1;o 2003, las adecuaciones a los planes y programas de estudios de las carreras que se indican del Centro de Formaci&#xF3;n T&#xE9;cnica Barros Arana, que se encuentran anexas y forman parte del presente decreto. Se modifican, en consecuencia, los decretos exentos de Educaci&#xF3;n que en cada caso se se&#xF1;alan, en el sentido de incorporar dichas adecuaciones:</div><br><div class=\"p\">Carrera&nbsp; : T&#xE9;cnico en Dibujo y Proyectos</div><div class=\"p\">T&#xED;tulo&nbsp;  : T&#xE9;cnico en Dibujo y Proyectos</div><div class=\"p\">&nbsp; &nbsp; &nbsp; &nbsp;  (Decreto exento N&#xBA; 395 del 28.12.90)</div><br><div class=\"p\">Carrera&nbsp; : T&#xE9;cnico en Procesamiento de Alimentos</div><div class=\"p\">T&#xED;tulo&nbsp;  : T&#xE9;cnico en Procesamiento de Alimentos</div><div class=\"p\">&nbsp; &nbsp; &nbsp; &nbsp;  (Decreto exento N&#xBA; 395 del 28.12.90)</div><br><div class=\"p\">Carrera&nbsp; : Saneamiento y Protecci&#xF3;n del Medio Ambiente</div><div class=\"p\">T&#xED;tulo&nbsp;  : T&#xE9;cnico en Saneamiento y Protecci&#xF3;n del</div><div class=\"p\">&nbsp; &nbsp; &nbsp; &nbsp;  Medio Ambiente</div><div class=\"p\">&nbsp; &nbsp; &nbsp; &nbsp; (Decreto exento N&#xBA; 93 del 05.04.99)</div><br><div class=\"p\">&nbsp; &nbsp;  Los nuevos planes y programas de estudios que se aprueban mediante este decreto pasar&#xE1;n a formar parte del proyecto institucional del Centro de Formaci&#xF3;n T&#xE9;cnica Barros Arana correspondiendo al Ministerio de Educaci&#xF3;n la verificaci&#xF3;n de su desarrollo.</div><br></div>", "i": 6431437}, {"t": "<div><div class=\"p\">&nbsp; &nbsp;  Santiago, 26 de junio de 2003.- Mar&#xED;a Ariadna Hornkohl Venegas, Subsecretaria de Educaci&#xF3;n.</div><br></div>", "i": 6431438}], "proyectos": [], "otrosSistemas": [], "jurisprudencia": [], "doctrina": [], "metadatos": {"tiene_notas": false, "tipos_numeros": [{"tipo": "2", "numero": "408 EXENTO", "abreviacion": "DTO", "descripcion": "Decreto", "compuesto": "DTO-408 EXENTO"}], "organismos": ["MINISTERIO DE EDUCACIÓN"], "titulo_norma": "EXTRACTO DE DECRETO Nº 408 EXENTO, DE 2003", "fuente": "Diario Oficial", "resumenes": [], "materias": [], "terminos_libres": [], "categorias_norma": [], "nombres_uso_comun": [], "paises_tratados": [], "organismos_tratados": [], "observaciones": [], "derogacion_tacita": [], "derogado": true, "fecha_promulgacion": "2003-06-06", "fecha_derogacion": "2021-12-31", "doble_articulado": false, "id_norma": "212428", "numero_fuente": "37608", "tipo_version": "2", "tipo_version_s": "Última Versión", "fecha_publicacion": "2003-07-14", "vigencias": [{"desde": "2021-12-31", "hasta": "", "tipo_version": "2", "tipo_version_s": "Última Versión"}, {"desde": "2003-07-14", "hasta": "2021-12-30", "tipo_version": "0", "tipo_version_s": "Texto Original"}], "vigencia": {"inicio_vigencia": "2021-12-31", "fin_vigencia": ""}, "vigencias_version_norma": [{"inicio_vigencia": "2003-07-14", "fin_vigencia": "2021-12-30", "tipo_version": "0"}, {"inicio_vigencia": "2021-12-31", "fin_vigencia": "2021-12-30", "tipo_version": "1"}, {"inicio_vigencia": "2021-12-31", "fin_vigencia": "", "tipo_version": "2"}], "eventos_pendientes": [], "vinculaciones": [{"text": "MODIFICACION", "url_part": "modificacion"}, {"text": "CONCORDANCIA", "url_part": "concordancia"}], "ingresado_por": "DVG", "fecha_ingreso": "2003-07-14", "fecha_version": "2021-08-24", "actualizado_por": "1289", "fecha_actualizacion_texto": "2021-08-24", "tipo_tratado": ""}, "alertas": [{"clase": "derogado", "texto": "Derogado", "mensaje": "Esta norma ha sido derogada el 31-DIC-2021"}], "alerta_global": {"m": ["Esta norma ha sido derogada el 31-DIC-2021"], "e": {"i": "", "p": "", "f": "", "t": ""}}, "estructura": [{"n": "Encabezado", "i": 6431436}, {"n": "Artículo", "i": 6431437, "t": 6}, {"n": "Promulgación", "i": 6431438}]}