{"html": [{"t": "<div><div class=\"p\">&nbsp; &nbsp; Por haber sido enviada con errores por la Subsecretar&#xED;a de Aviaci&#xF3;n la transcripci&#xF3;n de la ley N.o 5,534, publicada en el Diario Oficial, de 20 del mes en curso, a pedido de dicha Subsecretar&#xED;a se publica rectificada a continuaci&#xF3;n:</div><div class=\"p\">&nbsp; &nbsp; SUPLEMENTA EL PRESUPUESTO DEL MINISTERIO DE DEFENSA NACIONAL, SUBSECRETARIA DE AVIACION</div><div class=\"p\">&nbsp; &nbsp; Por cuanto el Congreso Nacional ha dado su aprobaci&#xF3;n al siguiente</div><div class=\"p\">&nbsp; &nbsp; Proyecto de ley:</div><br></div>", "i": 7170583}, {"t": "<div><div class=\"p\">&nbsp; &nbsp; Art&#xED;culo 1.o Suplem&#xE9;ntase el Presupuesto del Ministerio de Defensa Nacional, Subsecretar&#xED;a de Aviaci&#xF3;n, en la forma siguiente:</div><div class=\"p\"> 11/01/04/c Vi&#xE1;ticos_____________________$&nbsp; &nbsp;  10,000.00</div><div class=\"p\"> 11/01/04/d Jornales_____________________&nbsp; &nbsp; &nbsp; 14,000.00</div><div class=\"p\"> 11/01/04/f/1 Pasajes y fletes FF. CC.</div><div class=\"p\">&nbsp;  del Estado____________________________&nbsp; &nbsp; &nbsp; 15,000.00</div><div class=\"p\"> 11/01/04/f/2 Pasajes y fletes Empresas</div><div class=\"p\">&nbsp;  Privadas______________________________&nbsp; &nbsp; &nbsp; 50,000.00</div><div class=\"p\"> 11/01/04/g/3 Mat. y Art. de consumo_____&nbsp; &nbsp;  700,000.00</div><div class=\"p\"> 11/01/04/g/6 Medicamentos_______________&nbsp; &nbsp; &nbsp; 20,000.00</div><div class=\"p\"> 11/01/04/g/7 Cons. Material de Guerra___&nbsp; &nbsp; &nbsp; 10,000.00</div><div class=\"p\"> 11/01/04/g/8 Mantenimiento Ga. Qu&#xED;mica__&nbsp; &nbsp; &nbsp;  5,000.00</div><div class=\"p\"> 11/01/04/i/1 Alimentaci&#xF3;n_______________&nbsp; &nbsp;  100,000.00</div><div class=\"p\"> 11/01/04/i/3 Vestuario__________________&nbsp; &nbsp;  200,000.00</div><div class=\"p\"> 11/01/04/k Gastos generales_____________&nbsp; &nbsp; &nbsp; 20,000.00</div><div class=\"p\"> 11/01/04/o Gastos de raids______________&nbsp; &nbsp; &nbsp;  5,000.00</div><div class=\"p\"> 11/01/04/p/1 Previsi&#xF3;n__________________&nbsp; &nbsp; &nbsp; 66,600.00</div><div class=\"p\"> 11/01/04/q/1 Combustible y lubricantes__&nbsp; &nbsp;  800,000.00</div><div class=\"p\"> 11/01/04/q/2 Repuestos para aviones_____&nbsp; &nbsp;  60X0,000.00</div><div class=\"p\"> 11/01/04/v Varios e imprevistos_________&nbsp; &nbsp; &nbsp; 21,000.00</div><div class=\"p\"> 11/01/04/w Adquisiciones________________&nbsp; 12.637,000.00</div><div class=\"p\"> 11/01/04/x Subvenciones_________________&nbsp; &nbsp;  107,000.00</div><div class=\"p\"> 11/01/11&nbsp;  Construcciones, obras</div><div class=\"p\">&nbsp;  p&#xFA;blicas y auxilios extraordinarios___&nbsp; &nbsp;  308,000.00</div><div class=\"p\">&nbsp; &nbsp; &nbsp; &nbsp; &nbsp; &nbsp; &nbsp; &nbsp; &nbsp; &nbsp; &nbsp; &nbsp; &nbsp; &nbsp; &nbsp; &nbsp; &nbsp; &nbsp; &nbsp; &nbsp; ________________</div><div class=\"p\">&nbsp; &nbsp; &nbsp; &nbsp; &nbsp; &nbsp; &nbsp; &nbsp; &nbsp; &nbsp; &nbsp; &nbsp; &nbsp; &nbsp; &nbsp; &nbsp; &nbsp; &nbsp; &nbsp; &nbsp; $&nbsp; 15.688,600.00</div><div class=\"p\">&nbsp; &nbsp; &nbsp; &nbsp; &nbsp; &nbsp; &nbsp; &nbsp; &nbsp; &nbsp; &nbsp; &nbsp; &nbsp; &nbsp; &nbsp; &nbsp; &nbsp; &nbsp; &nbsp; &nbsp; ________________</div><br></div>", "i": 7170584}, {"t": "<div><div class=\"p\">&nbsp; &nbsp; Art. 2.o El mayor gasto de $ 15.688,600, que representan los suplementos a que se refiere el art&#xED;culo precedente, se cubrir&#xE1; con la mayor entrada que se produzca en la cuenta C-10 &quot;Arancel Aduanero&quot;. </div></div>", "i": 7170585}, {"t": "<div><div class=\"p\">&nbsp; &nbsp; Y por cuanto he tenido a bien aprobarlo y sancionarlo; por tanto, prom&#xFA;lguese y ll&#xE9;vese a efecto como ley de la Rep&#xFA;blica.</div><div class=\"p\">&nbsp; &nbsp; Santiago, diecinueve de Diciembre de mil novecientos treinta y cuatro.- ARTURO ALESSANDRI.- Emilio Bello C. </div></div>", "i": 7170586}], "proyectos": [], "otrosSistemas": [], "jurisprudencia": [], "doctrina": [], "metadatos": {"tiene_notas": false, "tipos_numeros": [{"tipo": "1", "numero": "5534", "abreviacion": "LEY", "descripcion": "Ley", "compuesto": "LEY-5534"}], "organismos": ["MINISTERIO DE DEFENSA NACIONAL"], "titulo_norma": "POR HABER SIDO ENVIADA CON ERRORES POR LA SUBSECRETARIA DE AVIACION LA TRANSCRIPCION DE LA LEY N° 5.534, PUBLICADA EN EL DIARIO OFICIAL, DE 20 DEL MES EN CURSO, A PEDIDO DE DICHA SUBSECRETARIA SE PUBLICA RECTIFICADA A CONTINUACION: SUPLEMENTA EL PRESUPUESTO DEL MINISTERIO DE DEFENSA NACIONAL, SUBSECRETARIA DE AVIACION", "fuente": "Diario Oficial", "resumenes": [], "materias": [], "terminos_libres": ["PRESUPUESTO GENERAL NACION", "1934", "MODIFICACION"], "categorias_norma": [], "nombres_uso_comun": [], "paises_tratados": [], "organismos_tratados": [], "observaciones": [], "derogacion_tacita": [], "derogado": false, "fecha_promulgacion": "1934-12-19", "doble_articulado": false, "id_norma": "25134", "numero_fuente": "17051", "tipo_version": "3", "tipo_version_s": "Única", "fecha_publicacion": "1934-12-22", "vigencias": [{"desde": "1934-12-22", "hasta": "", "tipo_version": "3", "tipo_version_s": "Única"}], "vigencia": {"inicio_vigencia": "1934-12-22", "fin_vigencia": ""}, "vigencias_version_norma": [{"inicio_vigencia": "1934-12-22", "fin_vigencia": "", "tipo_version": "3"}], "eventos_pendientes": [], "vinculaciones": [{"text": "MODIFICACION", "url_part": "modificacion"}], "fecha_version": "1934-12-22", "fecha_actualizacion_texto": "1934-12-22", "tipo_tratado": ""}, "alertas": [], "alerta_global": "", "estructura": [{"n": "Encabezado", "i": 7170583}, {"n": "Artículo 1", "i": 7170584, "t": 6}, {"n": "Artículo 2", "i": 7170585, "t": 6}, {"n": "Promulgación", "i": 7170586}]}