{"html": [{"t": "<div><div class=\"p\">&nbsp; &nbsp; MODIFICA LA LEY N&#xB0; 7,184, QUE AUTORIZA INVERTIR LA SUMA DE $ 850,000 EN LA CELEBRACION DE LAS FIESTAS BICENTENARIAS DE LA CIUDAD DE TALCA</div><div class=\"p\">&nbsp; &nbsp; Por cuanto el Congreso Nacional ha dado su aprobaci&#xF3;n al siguiente</div><div class=\"p\">&nbsp; &nbsp; Proyecto de ley:</div><br></div>", "i": 5963948}, {"t": "<div><div class=\"p\">&nbsp; &nbsp; &quot;Art&#xED;culo 1&#xB0;.- Reempl&#xE1;zase el art&#xED;culo 3&#xB0; de la ley N&#xB0; 7,184, de 25 de Junio de 1942, por el siguiente:</div><div class=\"p\">&nbsp; &nbsp; &quot;Art&#xED;culo 3&#xB0; La expresada suma deber&#xE1; invertirse en</div><div class=\"p\">la forma siguiente:</div><div class=\"p\"> a) Para un Teatro Popular________________&nbsp; $&nbsp; &nbsp; 500,000</div><div class=\"p\"> b) Para un campo deportivo en la</div><div class=\"p\">&nbsp; &nbsp; Poblaci&#xF3;n Oriente_____________________&nbsp; &nbsp; &nbsp; &nbsp; 50,000</div><div class=\"p\"> c) Para la celebraci&#xF3;n de campeonatos</div><div class=\"p\">&nbsp; &nbsp; deportivos____________________________&nbsp; &nbsp; &nbsp;  225,000</div><div class=\"p\"> d) Para la erecci&#xF3;n de un monumento a los</div><div class=\"p\">&nbsp; &nbsp; pr&#xF3;ceres de Talca_____________________&nbsp; &nbsp; &nbsp; &nbsp; 75,000&quot;</div><br></div>", "i": 5963949}, {"t": "<div><div class=\"p\">&nbsp; &nbsp; Art&#xED;culo 2&#xB0;.- La presente ley regir&#xE1; desde la fecha de su publicaci&#xF3;n en el Diario Oficial&quot;.</div><br></div>", "i": 5963950}, {"t": "<div><div class=\"p\">&nbsp; &nbsp; Y por cuanto he tenido a bien aprobarlo y sancionarlo; por tanto, prom&#xFA;lguese y ll&#xE9;vese a efecto como ley de la Rep&#xFA;blica.</div><div class=\"p\">&nbsp; &nbsp; Santiago, a cuatro de Febrero de mil novecientos cuarenta y tres.- JUAN ANTONIO RIOS M.- Gmo. del Pedregal.</div><br></div>", "i": 5963951}], "proyectos": [], "otrosSistemas": [], "jurisprudencia": [], "doctrina": [], "metadatos": {"tiene_notas": false, "tipos_numeros": [{"tipo": "1", "numero": "7414", "abreviacion": "LEY", "descripcion": "Ley", "compuesto": "LEY-7414"}], "organismos": ["MINISTERIO DE HACIENDA"], "titulo_norma": "MODIFICA LA LEY N° 7,184, QUE AUTORIZA INVERTIR LA\nSUMA DE $ 850,000 EN LA CELEBRACION DE LAS FIESTAS\nBICENTENARIAS DE LA CIUDAD DE TALCA", "fuente": "Diario Oficial", "resumenes": [], "materias": [], "terminos_libres": ["MODIFICACION", "LEY 7184", "INVERSION", "TEATRO POPULAR", "CAMPO DEPORTIVO", "CONSTRUCCION", "ERECCION", "MONUMENTO", "BICENTENARIO", "TALCA"], "categorias_norma": [], "nombres_uso_comun": [], "paises_tratados": [], "organismos_tratados": [], "observaciones": [], "derogacion_tacita": [], "derogado": false, "fecha_promulgacion": "1943-02-04", "doble_articulado": false, "id_norma": "25556", "numero_fuente": "19484", "tipo_version": "3", "tipo_version_s": "Única", "fecha_publicacion": "1943-02-13", "vigencias": [{"desde": "1943-02-13", "hasta": "", "tipo_version": "3", "tipo_version_s": "Única"}], "vigencia": {"inicio_vigencia": "1943-02-13", "fin_vigencia": ""}, "vigencias_version_norma": [{"inicio_vigencia": "1943-02-13", "fin_vigencia": "", "tipo_version": "3"}], "eventos_pendientes": [], "vinculaciones": [{"text": "MODIFICACION", "url_part": "modificacion"}], "fecha_version": "1943-02-13", "fecha_actualizacion_texto": "1943-02-13", "tipo_tratado": ""}, "alertas": [], "alerta_global": "", "estructura": [{"n": "Encabezado", "i": 5963948}, {"n": "Artículo 1", "i": 5963949, "t": 6}, {"n": "Artículo 2", "i": 5963950, "t": 6}, {"n": "Promulgación", "i": 5963951}]}