{"html": [{"t": "<div><div class=\"p\">&nbsp; &nbsp; DETERMINA FORMATO DE RECIBO QUE INDICA</div><div class=\"p\">&nbsp; &nbsp; N&#xFA;m. 707 exenta.- Santiago, 31 de mayo de 1995.- Visto: lo dispuesto en el art&#xED;culo 33 bis del decreto supremo N&#xB0; 405, de 1983, del Ministerio de Salud, Reglamento de Productos Psicotr&#xF3;picos y teniendo presente las facultades que me confieren los art&#xED;culos 4&#xB0; y 6&#xB0; del decreto ley N&#xB0; 2.763, de 1979, dicto la siguiente Resoluci&#xF3;n:</div><br></div>", "i": 6023353}, {"t": "<div><div class=\"p\">&nbsp; &nbsp; 1&#xB0;.- Apru&#xE9;base el siguiente formulario para los recibos de las muestras m&#xE9;dicas de productos farmac&#xE9;uticos que contienen las benzodiazepinas se&#xF1;aladas en los decretos supremos N&#xB0;s. 1.506, de 1993 y 1.186, de 1994, ambos del Ministerio de Salud, que se distribuyen por los Laboratorios de Producci&#xF3;n autorizados:</div><div class=\"p\"> _______________________________________________________</div><div class=\"p\"> | NOTA: VER DIARIO OFICIAL N&#xB0; 35.190 DEL DIA SABADO&nbsp;  |</div><div class=\"p\"> |&nbsp; &nbsp; &nbsp;  10 DE JUNIO DE 1995, PAGINA 2.&nbsp; &nbsp; &nbsp; &nbsp; &nbsp; &nbsp; &nbsp; &nbsp; |</div><div class=\"p\"> |_____________________________________________________|</div><div class=\"p\">&nbsp; &nbsp; 2&#xB0;.- El recibo ser&#xE1; extendido en original y al menos una copia foliada correlativamente por cada Laboratorio de Producci&#xF3;n, cuyo director t&#xE9;cnico conservar&#xE1; el original, quedando copia en poder del profesional.</div><br></div>", "i": 6023354}, {"t": "<div><div class=\"p\">&nbsp; &nbsp; An&#xF3;tese y publ&#xED;quese.- Fernando Mu&#xF1;oz Porras, Ministro de Salud Subrogante.</div><div class=\"p\">&nbsp; &nbsp; Lo que transcribo a Ud. para su conocimiento.- Saluda a Ud., Dr. Cleofe Molina Alvarez, Subsecretario (S) de Salud.</div><br></div>", "i": 6023355}], "proyectos": [], "otrosSistemas": [], "jurisprudencia": [], "doctrina": [], "metadatos": {"tiene_notas": false, "tipos_numeros": [{"tipo": "3", "numero": "707", "abreviacion": "RES", "descripcion": "Resolucion", "compuesto": "RES-707"}], "organismos": ["MINISTERIO DE SALUD"], "titulo_norma": "DETERMINA FORMATO DE RECIBO QUE INDICA", "fuente": "Diario Oficial", "resumenes": [], "materias": [], "terminos_libres": ["RECIBO MUESTRAS MEIDCAS", "PRODUCTOS FARMACEUTICOS", "FORMULARIO", "BENZODIAZEPINAS"], "categorias_norma": [], "nombres_uso_comun": [], "paises_tratados": [], "organismos_tratados": [], "observaciones": [], "derogacion_tacita": [], "derogado": false, "fecha_promulgacion": "1995-05-31", "doble_articulado": false, "id_norma": "39237", "numero_fuente": "35190", "tipo_version": "3", "tipo_version_s": "Única", "fecha_publicacion": "1995-06-10", "vigencias": [{"desde": "1995-06-10", "hasta": "", "tipo_version": "3", "tipo_version_s": "Única"}], "vigencia": {"inicio_vigencia": "1995-06-10", "fin_vigencia": ""}, "vigencias_version_norma": [{"inicio_vigencia": "1995-06-10", "fin_vigencia": "", "tipo_version": "3"}], "eventos_pendientes": [], "vinculaciones": [], "fecha_version": "1995-06-10", "fecha_actualizacion_texto": "1995-06-10", "tipo_tratado": ""}, "alertas": [], "alerta_global": "", "estructura": [{"n": "Encabezado", "i": 6023353}, {"n": "Artículo 1", "i": 6023354, "t": 6}, {"n": "Promulgación", "i": 6023355}]}