{"html": [{"t": "<div><div class=\"p\">&#xA0;</div></div>", "i": 6089703}, {"t": "<div><div class=\"p\">Por resoluci&#xF3;n SENDOS No. 290, de 31 de Marzo de 1989 y en base a la facultad otorgada por el Decreto Ley 2.050 de 1977, y DFL MOP. No. 22, de 1988, se expropi&#xF3; los lotes N&#xB0;s. 1 y 2 de los terrenos para la obra Agua Potable Rural, Sistema El Porvenir, Santa Rosa, El Roble, Las Pe&#xF1;as, V Regi&#xF3;n, que figuran a nombre de don Leonardo del C. Beltr&#xE1;n y otros, rol de aval&#xFA;os 152-397, comuna de Llay Llay, de 479 y 196 m2 de superficie, con los siguientes deslindes; Lote No. 1: Norte una l&#xED;nea de 5,5 mts. con camino p&#xFA;blico; Oriente, l&#xED;nea BE de 98,5 mts. con mismo propietario; Sur, l&#xED;nea DE de 5,5 mts. con lote 2; Poniente, l&#xED;nea AD de 94,00 mts. con mismo propietario; lote No. 2: Norte, l&#xED;nea CD de 6,5 mts. y de 5,5 mts. con lote 1; Oriente, l&#xED;nea FH. de 14 mts. con mismo propietario; Sur, l&#xED;nea GH de 14 mts. con mismo propietario; y Poniente, l&#xED;nea GC de 14 mts. con mismo propietario. La Comisi&#xF3;n de Peritos compuesta por los se&#xF1;ores Alvaro Verdejo Vidal, Fernando Cer&#xF3;n Leiva y Sergio Paravic Valdivia, fij&#xF3; con fecha 19 de noviembre de 1988, el valor provisional de la indemnizaci&#xF3;n en la suma de $ 30.625. La indemnizaci&#xF3;n se pagar&#xE1; al contado. La publicaci&#xF3;n se efect&#xFA;a en cumplimiento a lo dispuesto en el Art. 7 del Decreto Ley No. 2.186, de 1978.</div><br></div>", "i": 6089704}, {"t": "<div><div class=\"p\">Director Nacional de Obras Sanitarias.</div><br></div>", "i": 6089705}], "proyectos": [], "otrosSistemas": [], "jurisprudencia": [], "doctrina": [], "metadatos": {"tiene_notas": false, "tipos_numeros": [{"tipo": "3", "numero": "290", "abreviacion": "RES", "descripcion": "Resolucion", "compuesto": "RES-290"}], "organismos": ["SERVICIO NACIONAL DE OBRAS SANITARIAS"], "titulo_norma": "", "fuente": "Diario Oficial", "resumenes": [], "materias": [], "terminos_libres": [], "categorias_norma": [], "nombres_uso_comun": [], "paises_tratados": [], "organismos_tratados": [], "observaciones": ["EXTRACTO"], "derogacion_tacita": [], "derogado": false, "fecha_promulgacion": "1989-03-31", "doble_articulado": false, "id_norma": "91714", "numero_fuente": "33361", "tipo_version": "3", "tipo_version_s": "Única", "fecha_publicacion": "1989-05-02", "vigencias": [{"desde": "1989-05-02", "hasta": "", "tipo_version": "3", "tipo_version_s": "Única"}], "vigencia": {"inicio_vigencia": "1989-05-02", "fin_vigencia": ""}, "vigencias_version_norma": [{"inicio_vigencia": "1989-05-02", "fin_vigencia": "", "tipo_version": "3"}], "eventos_pendientes": [], "vinculaciones": [], "ingresado_por": "PGA", "fecha_ingreso": "1998-02-25", "fecha_version": "1989-05-02", "fecha_actualizacion_texto": "1989-05-02", "tipo_tratado": ""}, "alertas": [], "alerta_global": "", "estructura": [{"n": "Encabezado", "i": 6089703}, {"n": "Artículo", "i": 6089704, "t": 6}, {"n": "Promulgación", "i": 6089705}]}