{"html": [{"t": "<div><div class=\"p\">PRORROGA VIGENCIA DEL DECRETO ALCALDICIO No. 12 DE 1991 </div></div>", "i": 7231518}, {"t": "<div><div class=\"p\">N&#xFA;m. 23.- Illapel, 22 de Enero de 1992.- Vistos: Lo dispuesto en el art. No. 43&#xB0; del DFL No. 3.063 de 1979, sobre Rentas Municipales, el acuerdo del Consejo de Desarrollo Comunal, adoptado en la sesi&#xF3;n del d&#xED;a 13 de Enero de 1992 y las facultades que me confiere la Ley No.</div><div class=\"p\">18.695 Org&#xE1;nica Constitucional de Municipalidades.</div><div class=\"p\">1.- Prorr&#xF3;gase hasta el 31 de Diciembre de 1992 la vigencia del Decreto Alcaldicio No. 12 de 10 de Enero de 1991, sobre Ordenanza Local de Derechos Municipales, Concesiones, Permisos y Servicios, publicado en el Diario Oficial del 22 de Enero de 1991.</div><div class=\"p\">2.- El presente Decreto regir&#xE1; a contar de su publicaci&#xF3;n en el Diario Oficial.</div><br></div>", "i": 7231519}, {"t": "<div><div class=\"p\">An&#xF3;tese, publ&#xED;quese en el Diario Oficial, Inf&#xF3;rmese al se&#xF1;or Intendente Regional, transcr&#xED;base a todas las direcciones municipales y arch&#xED;vese.- Mar&#xED;a N. Jorquera Valencia, Alcalde(s).- Zaida Dabed Portillo, Secretaria (s). </div></div>", "i": 7231520}], "proyectos": [], "otrosSistemas": [], "jurisprudencia": [], "doctrina": [], "metadatos": {"tiene_notas": false, "tipos_numeros": [{"tipo": "2", "numero": "23", "abreviacion": "DTO", "descripcion": "Decreto", "compuesto": "DTO-23"}], "organismos": ["MUNICIPALIDAD DE ILLAPEL"], "titulo_norma": "PRORROGA VIGENCIA DEL DECRETO ALCALDICIO No. 12 DE 1991", "fuente": "Diario Oficial", "resumenes": [], "materias": [], "terminos_libres": [], "categorias_norma": [], "nombres_uso_comun": [], "paises_tratados": [], "organismos_tratados": [], "observaciones": [], "derogacion_tacita": [], "derogado": false, "fecha_promulgacion": "1992-01-22", "doble_articulado": false, "id_norma": "96920", "numero_fuente": "34180", "tipo_version": "3", "tipo_version_s": "Única", "fecha_publicacion": "1992-01-30", "vigencias": [{"desde": "1992-01-30", "hasta": "", "tipo_version": "3", "tipo_version_s": "Única"}], "vigencia": {"inicio_vigencia": "1992-01-30", "fin_vigencia": ""}, "vigencias_version_norma": [{"inicio_vigencia": "1992-01-30", "fin_vigencia": "", "tipo_version": "3"}], "eventos_pendientes": [], "vinculaciones": [{"text": "MODIFICACION", "url_part": "modificacion"}], "ingresado_por": "JCT", "fecha_ingreso": "1998-04-06", "fecha_version": "1992-01-30", "fecha_actualizacion_texto": "1992-01-30", "tipo_tratado": ""}, "alertas": [], "alerta_global": "", "estructura": [{"n": "Encabezado", "i": 7231518}, {"n": "Artículo", "i": 7231519, "t": 6}, {"n": "Promulgación", "i": 7231520}]}