{"html": [{"t": "<div><div class=\"p\">&#xA0;</div></div>", "i": 6110269}, {"t": "<div><div class=\"p\">&nbsp; &nbsp;  Por Decreto MOP. No 322,de 31 de marzo de 1998, se expropi&#xF3; el lote de terreno No 1, superficie lO8 m2., rol de aval&#xFA;o 40-9, comuna de Lolol obra Camino Ranquil-El Membrillo, Sector La Puntilla, y se acord&#xF3; precio de indemnizaci&#xF3;n con su propietaria Raquel Espina S&#xE1;nchez, ascendente a la cantidad de $428.039.</div><br></div>", "i": 6110270}, {"t": "<div><div class=\"p\">&nbsp; &nbsp;  Fiscal del Ministerio de Obras P&#xFA;blicas. </div></div>", "i": 6110271}], "proyectos": [], "otrosSistemas": [], "jurisprudencia": [], "doctrina": [], "metadatos": {"tiene_notas": false, "tipos_numeros": [{"tipo": "2", "numero": "322", "abreviacion": "DTO", "descripcion": "Decreto", "compuesto": "DTO-322"}], "organismos": ["MINISTERIO DE OBRAS PÚBLICAS", "FISCALÍA"], "titulo_norma": "", "fuente": "Diario Oficial", "resumenes": [], "materias": [], "terminos_libres": ["EXPROPIACION", "BIEN INMUEBLE", "LOLOL", "SEXTA REGION"], "categorias_norma": [], "nombres_uso_comun": [], "paises_tratados": [], "organismos_tratados": [], "observaciones": ["EXTRACTO"], "derogacion_tacita": [], "derogado": false, "fecha_promulgacion": "1998-03-31", "doble_articulado": false, "id_norma": "98851", "numero_fuente": "36054", "tipo_version": "3", "tipo_version_s": "Única", "fecha_publicacion": "1998-05-02", "vigencias": [{"desde": "1998-05-02", "hasta": "", "tipo_version": "3", "tipo_version_s": "Única"}], "vigencia": {"inicio_vigencia": "1998-05-02", "fin_vigencia": ""}, "vigencias_version_norma": [{"inicio_vigencia": "1998-05-02", "fin_vigencia": "", "tipo_version": "3"}], "eventos_pendientes": [], "vinculaciones": [], "ingresado_por": "JCT", "fecha_ingreso": "1998-05-12", "fecha_version": "1998-05-02", "fecha_actualizacion_texto": "1998-05-02", "tipo_tratado": ""}, "alertas": [], "alerta_global": "", "estructura": [{"n": "Encabezado", "i": 6110269}, {"n": "Artículo", "i": 6110270, "t": 6}, {"n": "Promulgación", "i": 6110271}]}